fs_omero_pyfs/__init__.py
fs_omero_pyfs/fs.py
fs_omero_pyfs/opener.py
fs_omero_pyfs-0.0.5.dist-info/LICENSE
fs_omero_pyfs-0.0.5.dist-info/METADATA
fs_omero_pyfs-0.0.5.dist-info/WHEEL
fs_omero_pyfs-0.0.5.dist-info/entry_points.txt
fs_omero_pyfs-0.0.5.dist-info/top_level.txt
fs_omero_pyfs-0.0.5.dist-info/RECORD
