Metadata-Version: 2.1
Name: fs-omero-pyfs
Version: 0.0.5
Summary: OMERO PyFilesystem2 filesystem
Home-page: https://github.com/manics/fs-omero-pyfs
Author: Simon Li
License: MIT
Platform: UNKNOWN
Classifier: License :: OSI Approved :: MIT License
Classifier: Operating System :: OS Independent
Classifier: Programming Language :: Python
Classifier: Programming Language :: Python :: 3
Classifier: Topic :: Scientific/Engineering
Classifier: Topic :: System :: Filesystems
Requires-Python: >=3.5
Requires-Dist: omero-py (>=5.6.dev9)
Requires-Dist: fs (<3,>=2)
